{
    "name": "§cПрицеливаться на колене",
    "author": "§eSPmojies - JIuc",
    "description": "Ведём прицельный огонь по врагу!",
    "emote":{
        "isLoop": "true",
        "returnTick": 20,
        "beginTick":0,
        "endTick":102,
        "stopTick":103,
        "degrees":false,
        "moves":[
            
            {
                "tick":20,
                "easing": "EASEINOUTQUAD",
                "turn": 0,
                "head":{
                    "x":-1.4650241020319754e-09
                }
            },
            {
                "tick":32,
                "easing": "EASEINOUTQUAD",
                "turn": 0,
                "head":{
                    "x":-1.4650241020319754e-09
                }
            },
            {
                "tick":45,
                "easing": "EASEINOUTQUAD",
                "turn": 0,
                "head":{
                    "x":-1.4650241020319754e-09
                }
            },
            {
                "tick":55,
                "easing": "EASEINOUTQUAD",
                "turn": 0,
                "head":{
                    "x":-1.4650241020319754e-09
                }
            },
            {
                "tick":67,
                "easing": "EASEINOUTQUAD",
                "turn": 0,
                "head":{
                    "x":-3.730773912025143e-09
                }
            },
            {
                "tick":80,
                "easing": "EASEINOUTQUAD",
                "turn": 0,
                "head":{
                    "x":-1.4650241020319754e-09
                }
            },
            {
                "tick":90,
                "easing": "EASEINOUTQUAD",
                "turn": 0,
                "head":{
                    "x":-1.4650241020319754e-09
                }
            },
            {
                "tick":102,
                "easing": "EASEINOUTQUAD",
                "turn": 0,
                "head":{
                    "x":-1.4650241020319754e-09
                }
            },
            {
                "tick":20,
                "easing": "EASEINOUTQUAD",
                "turn": 0,
                "head":{
                    "z":0.20937922596931458
                }
            },
            {
                "tick":32,
                "easing": "EASEINOUTQUAD",
                "turn": 0,
                "head":{
                    "z":0.222961887717247
                }
            },
            {
                "tick":45,
                "easing": "EASEINOUTQUAD",
                "turn": 0,
                "head":{
                    "z":0.20937922596931458
                }
            },
            {
                "tick":55,
                "easing": "EASEINOUTQUAD",
                "turn": 0,
                "head":{
                    "z":0.20937922596931458
                }
            },
            {
                "tick":67,
                "easing": "EASEINOUTQUAD",
                "turn": 0,
                "head":{
                    "z":0.22258099913597107
                }
            },
            {
                "tick":80,
                "easing": "EASEINOUTQUAD",
                "turn": 0,
                "head":{
                    "z":0.20937922596931458
                }
            },
            {
                "tick":90,
                "easing": "EASEINOUTQUAD",
                "turn": 0,
                "head":{
                    "z":0.20937922596931458
                }
            },
            {
                "tick":102,
                "easing": "EASEINOUTQUAD",
                "turn": 0,
                "head":{
                    "z":0.222961887717247
                }
            },
            {
                "tick":20,
                "easing": "EASEINOUTQUAD",
                "turn": 0,
                "head":{
                    "y":0.013472557067871094
                }
            },
            {
                "tick":32,
                "easing": "EASEINOUTQUAD",
                "turn": 0,
                "head":{
                    "y":-0.06355857849121094
                }
            },
            {
                "tick":45,
                "easing": "EASEINOUTQUAD",
                "turn": 0,
                "head":{
                    "y":0.013472557067871094
                }
            },
            {
                "tick":55,
                "easing": "EASEINOUTQUAD",
                "turn": 0,
                "head":{
                    "y":0.013472557067871094
                }
            },
            {
                "tick":67,
                "easing": "EASEINOUTQUAD",
                "turn": 0,
                "head":{
                    "y":-0.06139850616455078
                }
            },
            {
                "tick":80,
                "easing": "EASEINOUTQUAD",
                "turn": 0,
                "head":{
                    "y":0.013472557067871094
                }
            },
            {
                "tick":90,
                "easing": "EASEINOUTQUAD",
                "turn": 0,
                "head":{
                    "y":0.013472557067871094
                }
            },
            {
                "tick":102,
                "easing": "EASEINOUTQUAD",
                "turn": 0,
                "head":{
                    "y":-0.06355857849121094
                }
            },
            {
                "tick":20,
                "easing": "EASEINOUTQUAD",
                "turn": 0,
                "head":{
                    "pitch":-0.07748743891716003
                }
            },
            {
                "tick":32,
                "easing": "EASEINOUTQUAD",
                "turn": 0,
                "head":{
                    "pitch":-0.07748743891716003
                }
            },
            {
                "tick":45,
                "easing": "EASEINOUTQUAD",
                "turn": 0,
                "head":{
                    "pitch":-0.07748743891716003
                }
            },
            {
                "tick":55,
                "easing": "EASEINOUTQUAD",
                "turn": 0,
                "head":{
                    "pitch":-0.0445280596613884
                }
            },
            {
                "tick":67,
                "easing": "EASEINOUTQUAD",
                "turn": 0,
                "head":{
                    "pitch":-0.0445280596613884
                }
            },
            {
                "tick":80,
                "easing": "EASEINOUTQUAD",
                "turn": 0,
                "head":{
                    "pitch":-0.0445280596613884
                }
            },
            {
                "tick":90,
                "easing": "EASEINOUTQUAD",
                "turn": 0,
                "head":{
                    "pitch":-0.07748743891716003
                }
            },
            {
                "tick":102,
                "easing": "EASEINOUTQUAD",
                "turn": 0,
                "head":{
                    "pitch":-0.07748743891716003
                }
            },
            {
                "tick":20,
                "easing": "EASEINOUTQUAD",
                "turn": 0,
                "head":{
                    "roll":-0.30648067593574524
                }
            },
            {
                "tick":32,
                "easing": "EASEINOUTQUAD",
                "turn": 0,
                "head":{
                    "roll":-0.30648067593574524
                }
            },
            {
                "tick":45,
                "easing": "EASEINOUTQUAD",
                "turn": 0,
                "head":{
                    "roll":-0.30648067593574524
                }
            },
            {
                "tick":55,
                "easing": "EASEINOUTQUAD",
                "turn": 0,
                "head":{
                    "roll":-0.387608140707016
                }
            },
            {
                "tick":67,
                "easing": "EASEINOUTQUAD",
                "turn": 0,
                "head":{
                    "roll":-0.387608140707016
                }
            },
            {
                "tick":80,
                "easing": "EASEINOUTQUAD",
                "turn": 0,
                "head":{
                    "roll":-0.387608140707016
                }
            },
            {
                "tick":90,
                "easing": "EASEINOUTQUAD",
                "turn": 0,
                "head":{
                    "roll":-0.30648067593574524
                }
            },
            {
                "tick":102,
                "easing": "EASEINOUTQUAD",
                "turn": 0,
                "head":{
                    "roll":-0.30648067593574524
                }
            },
            {
                "tick":20,
                "easing": "EASEINOUTQUAD",
                "turn": 0,
                "head":{
                    "yaw":-0.024572670459747314
                }
            },
            {
                "tick":32,
                "easing": "EASEINOUTQUAD",
                "turn": 0,
                "head":{
                    "yaw":-0.024572670459747314
                }
            },
            {
                "tick":45,
                "easing": "EASEINOUTQUAD",
                "turn": 0,
                "head":{
                    "yaw":-0.024572670459747314
                }
            },
            {
                "tick":55,
                "easing": "EASEINOUTQUAD",
                "turn": 0,
                "head":{
                    "yaw":0.057577501982450485
                }
            },
            {
                "tick":67,
                "easing": "EASEINOUTQUAD",
                "turn": 0,
                "head":{
                    "yaw":0.057577501982450485
                }
            },
            {
                "tick":80,
                "easing": "EASEINOUTQUAD",
                "turn": 0,
                "head":{
                    "yaw":0.057577501982450485
                }
            },
            {
                "tick":90,
                "easing": "EASEINOUTQUAD",
                "turn": 0,
                "head":{
                    "yaw":-0.024572670459747314
                }
            },
            {
                "tick":102,
                "easing": "EASEINOUTQUAD",
                "turn": 0,
                "head":{
                    "yaw":-0.024572670459747314
                }
            },
            {
                "tick":20,
                "easing": "EASEINOUTQUAD",
                "turn": 0,
                "torso":{
                    "x":0.0
                }
            },
            {
                "tick":20,
                "easing": "EASEINOUTQUAD",
                "turn": 0,
                "torso":{
                    "z":-0.0
                }
            },
            {
                "tick":20,
                "easing": "EASEINOUTQUAD",
                "turn": 0,
                "torso":{
                    "y":-0.30899208784103394
                }
            },
            {
                "tick":20,
                "easing": "EASEINOUTQUAD",
                "turn": 0,
                "torso":{
                    "pitch":0.0
                }
            },
            {
                "tick":20,
                "easing": "EASEINOUTQUAD",
                "turn": 0,
                "torso":{
                    "roll":-0.0
                }
            },
            {
                "tick":20,
                "easing": "EASEINOUTQUAD",
                "turn": 0,
                "torso":{
                    "yaw":0.0
                }
            },
            {
                "tick":20,
                "easing": "EASEINOUTQUAD",
                "turn": 0,
                "torso":{
                    "bend":0.1745329201221466
                }
            },
            {
                "tick":102,
                "easing": "EASEINOUTQUAD",
                "turn": 0,
                "torso":{
                    "bend":0.1745329201221466
                }
            },
            {
                "tick":8,
                "easing": "EASEINOUTQUAD",
                "turn": 0,
                "rightArm":{
                    "x":-5.0
                }
            },
            {
                "tick":20,
                "easing": "EASEINOUTQUAD",
                "turn": 0,
                "rightArm":{
                    "x":-3.235011339187622
                }
            },
            {
                "tick":102,
                "easing": "EASEINOUTQUAD",
                "turn": 0,
                "rightArm":{
                    "x":-3.235011339187622
                }
            },
            {
                "tick":8,
                "easing": "EASEINOUTQUAD",
                "turn": 0,
                "rightArm":{
                    "z":-0.0
                }
            },
            {
                "tick":20,
                "easing": "EASEINOUTQUAD",
                "turn": 0,
                "rightArm":{
                    "z":0.7297279238700867
                }
            },
            {
                "tick":102,
                "easing": "EASEINOUTQUAD",
                "turn": 0,
                "rightArm":{
                    "z":0.7297279238700867
                }
            },
            {
                "tick":8,
                "easing": "EASEINOUTQUAD",
                "turn": 0,
                "rightArm":{
                    "y":2.0
                }
            },
            {
                "tick":20,
                "easing": "EASEINOUTQUAD",
                "turn": 0,
                "rightArm":{
                    "y":2.13198184967041
                }
            },
            {
                "tick":102,
                "easing": "EASEINOUTQUAD",
                "turn": 0,
                "rightArm":{
                    "y":2.13198184967041
                }
            },
            {
                "tick":8,
                "easing": "EASEINOUTQUAD",
                "turn": 0,
                "rightArm":{
                    "pitch":-0.0
                }
            },
            {
                "tick":20,
                "easing": "EASEINOUTQUAD",
                "turn": 0,
                "rightArm":{
                    "pitch":-1.2388205528259277
                }
            },
            {
                "tick":102,
                "easing": "EASEINOUTQUAD",
                "turn": 0,
                "rightArm":{
                    "pitch":-1.2388205528259277
                }
            },
            {
                "tick":8,
                "easing": "EASEINOUTQUAD",
                "turn": 0,
                "rightArm":{
                    "roll":-0.0
                }
            },
            {
                "tick":20,
                "easing": "EASEINOUTQUAD",
                "turn": 0,
                "rightArm":{
                    "roll":-0.025033649057149887
                }
            },
            {
                "tick":102,
                "easing": "EASEINOUTQUAD",
                "turn": 0,
                "rightArm":{
                    "roll":-0.025033649057149887
                }
            },
            {
                "tick":8,
                "easing": "EASEINOUTQUAD",
                "turn": 0,
                "rightArm":{
                    "yaw":-0.0
                }
            },
            {
                "tick":20,
                "easing": "EASEINOUTQUAD",
                "turn": 0,
                "rightArm":{
                    "yaw":-0.08987818658351898
                }
            },
            {
                "tick":102,
                "easing": "EASEINOUTQUAD",
                "turn": 0,
                "rightArm":{
                    "yaw":-0.08987818658351898
                }
            },
            {
                "tick":20,
                "easing": "EASEINOUTQUAD",
                "turn": 0,
                "rightArm":{
                    "bend":-0.5125006437301636
                }
            },
            {
                "tick":40,
                "easing": "EASEINOUTQUAD",
                "turn": 0,
                "rightArm":{
                    "bend":-0.5742838382720947
                }
            },
            {
                "tick":60,
                "easing": "EASEINOUTQUAD",
                "turn": 0,
                "rightArm":{
                    "bend":-0.5125006437301636
                }
            },
            {
                "tick":80,
                "easing": "EASEINOUTQUAD",
                "turn": 0,
                "rightArm":{
                    "bend":-0.5742838382720947
                }
            },
            {
                "tick":102,
                "easing": "EASEINOUTQUAD",
                "turn": 0,
                "rightArm":{
                    "bend":-0.5125006437301636
                }
            },
            {
                "tick":8,
                "easing": "EASEINOUTQUAD",
                "turn": 0,
                "leftArm":{
                    "x":5.0
                }
            },
            {
                "tick":20,
                "easing": "EASEINOUTQUAD",
                "turn": 0,
                "leftArm":{
                    "x":4.011394500732422
                }
            },
            {
                "tick":40,
                "easing": "EASEINOUTQUAD",
                "turn": 0,
                "leftArm":{
                    "x":4.011394500732422
                }
            },
            {
                "tick":60,
                "easing": "EASEINOUTQUAD",
                "turn": 0,
                "leftArm":{
                    "x":4.011394500732422
                }
            },
            {
                "tick":80,
                "easing": "EASEINOUTQUAD",
                "turn": 0,
                "leftArm":{
                    "x":4.011394500732422
                }
            },
            {
                "tick":102,
                "easing": "EASEINOUTQUAD",
                "turn": 0,
                "leftArm":{
                    "x":4.011394500732422
                }
            },
            {
                "tick":8,
                "easing": "EASEINOUTQUAD",
                "turn": 0,
                "leftArm":{
                    "z":-0.0
                }
            },
            {
                "tick":20,
                "easing": "EASEINOUTQUAD",
                "turn": 0,
                "leftArm":{
                    "z":-1.1063733100891113
                }
            },
            {
                "tick":40,
                "easing": "EASEINOUTQUAD",
                "turn": 0,
                "leftArm":{
                    "z":-1.1379231214523315
                }
            },
            {
                "tick":60,
                "easing": "EASEINOUTQUAD",
                "turn": 0,
                "leftArm":{
                    "z":-1.1063733100891113
                }
            },
            {
                "tick":80,
                "easing": "EASEINOUTQUAD",
                "turn": 0,
                "leftArm":{
                    "z":-1.1379231214523315
                }
            },
            {
                "tick":102,
                "easing": "EASEINOUTQUAD",
                "turn": 0,
                "leftArm":{
                    "z":-1.1063733100891113
                }
            },
            {
                "tick":8,
                "easing": "EASEINOUTQUAD",
                "turn": 0,
                "leftArm":{
                    "y":2.0
                }
            },
            {
                "tick":20,
                "easing": "EASEINOUTQUAD",
                "turn": 0,
                "leftArm":{
                    "y":3.1802291870117188
                }
            },
            {
                "tick":40,
                "easing": "EASEINOUTQUAD",
                "turn": 0,
                "leftArm":{
                    "y":3.1206283569335938
                }
            },
            {
                "tick":60,
                "easing": "EASEINOUTQUAD",
                "turn": 0,
                "leftArm":{
                    "y":3.1802291870117188
                }
            },
            {
                "tick":80,
                "easing": "EASEINOUTQUAD",
                "turn": 0,
                "leftArm":{
                    "y":3.1206283569335938
                }
            },
            {
                "tick":102,
                "easing": "EASEINOUTQUAD",
                "turn": 0,
                "leftArm":{
                    "y":3.1802291870117188
                }
            },
            {
                "tick":8,
                "easing": "EASEINOUTQUAD",
                "turn": 0,
                "leftArm":{
                    "pitch":-0.0
                }
            },
            {
                "tick":20,
                "easing": "EASEINOUTQUAD",
                "turn": 0,
                "leftArm":{
                    "pitch":-1.9623239040374756
                }
            },
            {
                "tick":40,
                "easing": "EASEINOUTQUAD",
                "turn": 0,
                "leftArm":{
                    "pitch":-1.9818496704101562
                }
            },
            {
                "tick":60,
                "easing": "EASEINOUTQUAD",
                "turn": 0,
                "leftArm":{
                    "pitch":-1.9623239040374756
                }
            },
            {
                "tick":80,
                "easing": "EASEINOUTQUAD",
                "turn": 0,
                "leftArm":{
                    "pitch":-1.9818496704101562
                }
            },
            {
                "tick":102,
                "easing": "EASEINOUTQUAD",
                "turn": 0,
                "leftArm":{
                    "pitch":-1.9623239040374756
                }
            },
            {
                "tick":8,
                "easing": "EASEINOUTQUAD",
                "turn": 0,
                "leftArm":{
                    "roll":-0.0
                }
            },
            {
                "tick":20,
                "easing": "EASEINOUTQUAD",
                "turn": 0,
                "leftArm":{
                    "roll":-1.2639683485031128
                }
            },
            {
                "tick":40,
                "easing": "EASEINOUTQUAD",
                "turn": 0,
                "leftArm":{
                    "roll":-1.2677719593048096
                }
            },
            {
                "tick":60,
                "easing": "EASEINOUTQUAD",
                "turn": 0,
                "leftArm":{
                    "roll":-1.2639683485031128
                }
            },
            {
                "tick":80,
                "easing": "EASEINOUTQUAD",
                "turn": 0,
                "leftArm":{
                    "roll":-1.2677719593048096
                }
            },
            {
                "tick":102,
                "easing": "EASEINOUTQUAD",
                "turn": 0,
                "leftArm":{
                    "roll":-1.2639683485031128
                }
            },
            {
                "tick":8,
                "easing": "EASEINOUTQUAD",
                "turn": 0,
                "leftArm":{
                    "yaw":-0.0
                }
            },
            {
                "tick":20,
                "easing": "EASEINOUTQUAD",
                "turn": 0,
                "leftArm":{
                    "yaw":0.2263847440481186
                }
            },
            {
                "tick":40,
                "easing": "EASEINOUTQUAD",
                "turn": 0,
                "leftArm":{
                    "yaw":0.16552360355854034
                }
            },
            {
                "tick":60,
                "easing": "EASEINOUTQUAD",
                "turn": 0,
                "leftArm":{
                    "yaw":0.2263847440481186
                }
            },
            {
                "tick":80,
                "easing": "EASEINOUTQUAD",
                "turn": 0,
                "leftArm":{
                    "yaw":0.16552360355854034
                }
            },
            {
                "tick":102,
                "easing": "EASEINOUTQUAD",
                "turn": 0,
                "leftArm":{
                    "yaw":0.2263847440481186
                }
            },
            {
                "tick":20,
                "easing": "EASEINOUTQUAD",
                "turn": 0,
                "leftArm":{
                    "bend":-0.7389817237854004
                }
            },
            {
                "tick":102,
                "easing": "EASEINOUTQUAD",
                "turn": 0,
                "leftArm":{
                    "bend":-0.7389817237854004
                }
            },
            {
                "tick":20,
                "easing": "EASEINOUTQUAD",
                "turn": 0,
                "rightLeg":{
                    "x":-1.9
                }
            },
            {
                "tick":20,
                "easing": "EASEINOUTQUAD",
                "turn": 0,
                "rightLeg":{
                    "z":0.1
                }
            },
            {
                "tick":20,
                "easing": "EASEINOUTQUAD",
                "turn": 0,
                "rightLeg":{
                    "y":12.0
                }
            },
            {
                "tick":20,
                "easing": "EASEINOUTQUAD",
                "turn": 0,
                "rightLeg":{
                    "pitch":-1.3962633609771729
                }
            },
            {
                "tick":20,
                "easing": "EASEINOUTQUAD",
                "turn": 0,
                "rightLeg":{
                    "roll":-0.0
                }
            },
            {
                "tick":20,
                "easing": "EASEINOUTQUAD",
                "turn": 0,
                "rightLeg":{
                    "yaw":-0.0
                }
            },
            {
                "tick":20,
                "easing": "EASEINOUTQUAD",
                "turn": 0,
                "rightLeg":{
                    "bend":1.3962633609771729
                }
            },
            {
                "tick":20,
                "easing": "EASEINOUTQUAD",
                "turn": 0,
                "leftLeg":{
                    "x":1.9
                }
            },
            {
                "tick":20,
                "easing": "EASEINOUTQUAD",
                "turn": 0,
                "leftLeg":{
                    "z":-0.1
                }
            },
            {
                "tick":20,
                "easing": "EASEINOUTQUAD",
                "turn": 0,
                "leftLeg":{
                    "y":11.206933557987213
                }
            },
            {
                "tick":20,
                "easing": "EASEINOUTQUAD",
                "turn": 0,
                "leftLeg":{
                    "pitch":0.12217304110527039
                }
            },
            {
                "tick":20,
                "easing": "EASEINOUTQUAD",
                "turn": 0,
                "leftLeg":{
                    "roll":-0.0
                }
            },
            {
                "tick":20,
                "easing": "EASEINOUTQUAD",
                "turn": 0,
                "leftLeg":{
                    "yaw":-0.0
                }
            },
            {
                "tick":20,
                "easing": "EASEINOUTQUAD",
                "turn": 0,
                "leftLeg":{
                    "bend":1.4486232995986938
                }
            }
        ]
    }
}